graphmaker/__init__.py
graphmaker/model/__init__.py
graphmaker/model/extract/__init__.py
graphmaker/model/extract/_dataprovider.py
graphmaker/model/extract/pandas.py
graphmaker/model/extract/parquet.py
graphmaker/model/extract/xls.py
graphmaker/model/load/__init__.py
graphmaker/model/load/neo4j.py
graphmaker/model/transform/__init__.py
graphmaker/model/transform/edge.py
graphmaker/model/transform/node.py
graphmaker-1.1.0.dist-info/METADATA
graphmaker-1.1.0.dist-info/WHEEL
graphmaker-1.1.0.dist-info/RECORD
