Metadata-Version: 2.3
Name: graphmaker
Version: 1.1.0
Summary: 
License: MIT
Author: Leonardo Christino
Author-email: lchristino@graphpolaris.com
Requires-Python: >=3.11
Classifier: License :: OSI Approved :: MIT License
Classifier: Programming Language :: Python :: 3
Classifier: Programming Language :: Python :: 3.11
Classifier: Programming Language :: Python :: 3.12
Classifier: Programming Language :: Python :: 3.13
Requires-Dist: neo4j (>=5.28.1,<6.0.0)
Requires-Dist: numpy (>=2.2.5,<3.0.0)
Requires-Dist: openpyxl (>=3.1.5,<4.0.0)
Requires-Dist: pandas (>=2.2.3,<3.0.0)
Requires-Dist: pyarrow (>=20.0.0,<21.0.0)
Requires-Dist: tqdm (>=4.67.1,<5.0.0)
